nextlinegraphql/__about__.py
nextlinegraphql/__init__.py
nextlinegraphql/factory.py
nextlinegraphql/py.typed
nextlinegraphql/config/__init__.py
nextlinegraphql/config/default.toml
nextlinegraphql/custom/__init__.py
nextlinegraphql/custom/strawberry.py
nextlinegraphql/hook/__init__.py
nextlinegraphql/hook/spec.py
nextlinegraphql/plugins/__init__.py
nextlinegraphql/plugins/ctrl/__init__.py
nextlinegraphql/plugins/ctrl/cache.py
nextlinegraphql/plugins/ctrl/default.toml
nextlinegraphql/plugins/ctrl/example_script/__init__.py
nextlinegraphql/plugins/ctrl/example_script/script.py
nextlinegraphql/plugins/ctrl/example_script/script2.py
nextlinegraphql/plugins/ctrl/example_script/script_asyncio.py
nextlinegraphql/plugins/ctrl/example_script/script_scratch.py
nextlinegraphql/plugins/ctrl/example_script/script_threading.py
nextlinegraphql/plugins/ctrl/graphql/__init__.py
nextlinegraphql/plugins/ctrl/graphql/mutations/Exec.gql
nextlinegraphql/plugins/ctrl/graphql/mutations/Interrupt.gql
nextlinegraphql/plugins/ctrl/graphql/mutations/Kill.gql
nextlinegraphql/plugins/ctrl/graphql/mutations/LoadExampleScript.gql
nextlinegraphql/plugins/ctrl/graphql/mutations/Reset.gql
nextlinegraphql/plugins/ctrl/graphql/mutations/RunAndContinue.gql
nextlinegraphql/plugins/ctrl/graphql/mutations/SendPdbCommand.gql
nextlinegraphql/plugins/ctrl/graphql/mutations/Terminate.gql
nextlinegraphql/plugins/ctrl/graphql/queries/ContinuousEnabled.gql
nextlinegraphql/plugins/ctrl/graphql/queries/Exception.gql
nextlinegraphql/plugins/ctrl/graphql/queries/RunNo.gql
nextlinegraphql/plugins/ctrl/graphql/queries/Source.gql
nextlinegraphql/plugins/ctrl/graphql/queries/SourceLine.gql
nextlinegraphql/plugins/ctrl/graphql/queries/State.gql
nextlinegraphql/plugins/ctrl/graphql/queries/TraceIds.gql
nextlinegraphql/plugins/ctrl/graphql/subscriptions/ContinuousEnabled.gql
nextlinegraphql/plugins/ctrl/graphql/subscriptions/Counter.gql
nextlinegraphql/plugins/ctrl/graphql/subscriptions/Prompting.gql
nextline_graphql-0.8.1.dist-info/METADATA
nextline_graphql-0.8.1.dist-info/WHEEL
nextline_graphql-0.8.1.dist-info/licenses/LICENSE
nextline_graphql-0.8.1.dist-info/RECORD
