Metadata-Version: 2.4
Name: nextline-graphql
Version: 0.8.1
Summary: Python framework for building plugin‑based HTTP API servers.
Project-URL: Homepage, https://github.com/simonsobs/nextline
Author-email: Tai Sakuma <tai.sakuma@gmail.com>
License-Expression: MIT
License-File: LICENSE
Classifier: Development Status :: 4 - Beta
Classifier: Intended Audience :: Science/Research
Classifier: License :: OSI Approved :: MIT License
Classifier: Programming Language :: Python :: 3.10
Classifier: Programming Language :: Python :: 3.11
Classifier: Programming Language :: Python :: 3.12
Classifier: Programming Language :: Python :: 3.13
Classifier: Programming Language :: Python :: 3.14
Requires-Python: >=3.10
Requires-Dist: apluggy>=1.0
Requires-Dist: async-asgi-testclient>=1.4
Requires-Dist: dynaconf>=3.2
Requires-Dist: nextline>=0.7.15
Requires-Dist: rich>=13.6
Requires-Dist: starlette>=0.48
Requires-Dist: strawberry-graphql>=0.283.2
Requires-Dist: websockets>=12.0
Provides-Extra: dev
Requires-Dist: black; extra == 'dev'
Requires-Dist: flake8; extra == 'dev'
Requires-Dist: logging-tree; extra == 'dev'
Requires-Dist: mypy; extra == 'dev'
Requires-Dist: tox; extra == 'dev'
Requires-Dist: twine; extra == 'dev'
Requires-Dist: uvicorn; extra == 'dev'
Provides-Extra: tests
Requires-Dist: hypothesis>=6.130; extra == 'tests'
Requires-Dist: nextline-test-utils>=0.1.2; extra == 'tests'
Requires-Dist: pytest-asyncio>=0.21; extra == 'tests'
Requires-Dist: pytest-cov>=4.1; extra == 'tests'
Requires-Dist: pytest-timeout>=2.2; extra == 'tests'
Requires-Dist: pytest>=8.0; extra == 'tests'
Requires-Dist: syrupy>=4.7; extra == 'tests'
